{
  "forecastId": "37467-homo_full-pro-2",
  "questionId": 37467,
  "condition": "homo_full",
  "model": "pro",
  "position": 2,
  "infoLabel": "full",
  "groupId": "37467-homo_full",
  "independentForecastId": "37467-pro-full-2",
  "otherForecastIds": [
    "37467-pro-full-1",
    "37467-pro-full-3"
  ],
  "forecast": {
    "review": "My two colleagues and I have reached a strong consensus on the core facts of this question: Beyond Meat is in a state of severe financial distress, but the newly secured $100 million financing facility on May 7, 2025, provides a critical short-term liquidity bridge. We all agree this new loan makes a bankruptcy filing before July 1, 2025, highly unlikely. The primary disagreement lies in the quantification of that 'highly unlikely' probability, with my initial 2% being at the low end and my colleagues at 5% and 8%.\n\nTheir reasoning for a higher probability is convincing in that it forces me to consider more specific failure mechanisms beyond a generic 'black swan' event. Forecaster 3's mention of a potential covenant breach on the new loan is a particularly salient point. While performance covenants are typically tested quarterly, a 'Material Adverse Change' clause or another event of default could theoretically be triggered by a sufficiently rapid and unforeseen operational or sales collapse in the next seven weeks. This introduces a more plausible, albeit still low-probability, pathway to a near-term filing than I had initially modeled.\n\nHowever, I find the 5-8% range to be too high. It seems to overweight the company's long-term fragility and apply it to a very short-term window where a specific, countervailing force—the new loan—is dominant. The new senior secured lenders have performed due diligence and have a strong incentive to prevent a bankruptcy filing in the immediate term to protect their investment. Their action of lending money is a powerful signal that they do not foresee a collapse within weeks. Therefore, while I acknowledge the slightly higher risk highlighted by my colleagues, I remain more confident than them in the short-term stability this financing provides.",
    "rationale": "After reviewing my colleagues' analyses, I am making a minor upward revision to my forecast. My initial reasoning remains largely the same: the new $100 million financing facility secured on May 7, 2025, is the determinative factor for this short-term forecast. This capital injection, on top of existing cash, provides a sufficient runway to operate well beyond the July 1 deadline, making an imminent bankruptcy filing extremely improbable. The pay-in-kind interest feature further reduces near-term cash burn.\n\nI am increasing my probability from 2% to 3% based on the deliberation. The other forecasters correctly emphasized the extreme underlying financial distress. While I believe this is primarily a medium-to-long-term risk, their arguments convinced me to slightly increase the weight I assign to a 'rapid accident' scenario. Specifically, Forecaster 3's point regarding a potential covenant breach on the new loan is a valid, specific risk I may have under-weighted. An exceptionally poor start to Q2 or another unforeseen negative event could theoretically trigger such a breach or a Material Adverse Change clause, forcing a default and subsequent bankruptcy filing even within this short window.\n\nThis adjustment from 2% to 3% reflects a shift from pricing in only 'black swan' risks to also including a small probability for a more specific, rapid-collapse scenario stemming from the company's fragility. However, I remain well below my colleagues' 5% and 8% forecasts because I believe the act of securing new senior financing is a very strong signal of solvency for at least the next few months, and that the probability of a default-triggering event occurring in the next seven weeks remains very low.",
    "probability": 3
  },
  "usage": {
    "inputTokens": 2078,
    "outputTokens": 2736,
    "totalTokens": 4814,
    "reasoningTokens": 1995,
    "cachedInputTokens": 0
  }
}